17MonIP-0.2.6.dist-info/top_level.txt
17MonIP-0.2.6.dist-info/RECORD
17MonIP-0.2.6.dist-info/WHEEL
17MonIP-0.2.6.dist-info/DESCRIPTION.rst
17MonIP-0.2.6.dist-info/entry_points.txt
17MonIP-0.2.6.dist-info/metadata.json
17MonIP-0.2.6.dist-info/METADATA
IP/cmd.py
IP/17monipdb.dat
IP/__init__.py
IP/ip.py
