Metadata-Version: 2.0
Name: 17MonIP
Version: 0.2.6
Summary: IP search based on 17mon.cn, the best IP database for China.
Home-page: http://lxyu.github.io/17monip/
Author: Lx Yu
Author-email: github@lxyu.net
License: MIT
Platform: UNKNOWN
Classifier: Development Status :: 5 - Production/Stable
Classifier: License :: OSI Approved :: MIT License
Classifier: Intended Audience :: Developers
Classifier: Programming Language :: Python :: 2.6
Classifier: Programming Language :: Python :: 2.7
Classifier: Programming Language :: Python :: 3.2
Classifier: Programming Language :: Python :: 3.3
Classifier: Programming Language :: Python :: 3.4
Classifier: Programming Language :: Python :: Implementation :: CPython
Classifier: Programming Language :: Python :: Implementation :: PyPy
Provides-Extra: dev
Requires-Dist: flake8 (>=2.2.0); extra == 'dev'
Requires-Dist: pytest (>=2.6.0); extra == 'dev'
